django_service_views/__init__.py
django_service_views/apps.py
django_service_views/py.typed
django_service_views/views.py
django_service_views-0.1.0.dist-info/METADATA
django_service_views-0.1.0.dist-info/WHEEL
django_service_views-0.1.0.dist-info/licenses/LICENSE
django_service_views-0.1.0.dist-info/RECORD
