Metadata-Version: 2.4
Name: django-service-views
Version: 0.1.0
Summary: Django class-based views for service layer pattern
Project-URL: Homepage, https://github.com/yourusername/django-service-views
Project-URL: Repository, https://github.com/yourusername/django-service-views
Project-URL: Issues, https://github.com/yourusername/django-service-views/issues
Author-email: Austin <austin@example.com>
License: MIT
License-File: LICENSE
Keywords: cbv,class-based-views,django,service-layer,views
Classifier: Development Status :: 4 - Beta
Classifier: Framework :: Django
Classifier: Framework :: Django :: 4.2
Classifier: Framework :: Django :: 5.0
Classifier: Framework :: Django :: 5.1
Classifier: Intended Audience :: Developers
Classifier: License :: OSI Approved :: MIT License
Classifier: Operating System :: OS Independent
Classifier: Programming Language :: Python :: 3
Classifier: Programming Language :: Python :: 3.8
Classifier: Programming Language :: Python :: 3.9
Classifier: Programming Language :: Python :: 3.10
Classifier: Programming Language :: Python :: 3.11
Classifier: Programming Language :: Python :: 3.12
Classifier: Topic :: Software Development :: Libraries :: Python Modules
Requires-Python: >=3.8
Requires-Dist: django>=4.2
